nullbr_python/__init__.py
nullbr_python/cli.py
nullbr_python/models/__init__.py
nullbr_python/models/base.py
nullbr_python/models/collection.py
nullbr_python/models/movie.py
nullbr_python/models/search.py
nullbr_python/models/tv.py
nullbr_python-0.1.3.dist-info/METADATA
nullbr_python-0.1.3.dist-info/WHEEL
nullbr_python-0.1.3.dist-info/entry_points.txt
nullbr_python-0.1.3.dist-info/licenses/LICENSE
nullbr_python-0.1.3.dist-info/RECORD
