Metadata-Version: 2.4
Name: nullbr-python
Version: 0.1.3
Summary: Python SDK for Nullbr API - 用于访问 Nullbr API 的 Python SDK
Project-URL: Homepage, https://github.com/iLay1678/nullbr_python
Project-URL: Documentation, https://github.com/iLay1678/nullbr_python/blob/main/README.md
Project-URL: Repository, https://github.com/iLay1678/nullbr_python
Project-URL: Bug Tracker, https://github.com/iLay1678/nullbr_python/issues
Author-email: iLay1678 <ifwangs400@gmail.com>
Maintainer-email: iLay1678 <ifwangs400@gmail.com>
License: MIT
License-File: LICENSE
Keywords: api,movies,nullbr,sdk,tmdb,tv
Classifier: Development Status :: 4 - Beta
Classifier: Intended Audience :: Developers
Classifier: License :: OSI Approved :: MIT License
Classifier: Operating System :: OS Independent
Classifier: Programming Language :: Python :: 3
Classifier: Programming Language :: Python :: 3.9
Classifier: Programming Language :: Python :: 3.10
Classifier: Programming Language :: Python :: 3.11
Classifier: Programming Language :: Python :: 3.12
Classifier: Topic :: Internet :: WWW/HTTP
Classifier: Topic :: Multimedia :: Video
Classifier: Topic :: Software Development :: Libraries :: Python Modules
Requires-Python: >=3.9
Requires-Dist: httpx[http2,socks]>=0.28.1
Requires-Dist: python-dotenv>=1.1.0
Provides-Extra: dev
Requires-Dist: black>=23.0.0; extra == 'dev'
Requires-Dist: isort>=5.12.0; extra == 'dev'
Requires-Dist: pytest-cov>=4.0.0; extra == 'dev'
Requires-Dist: pytest>=7.0.0; extra == 'dev'
Requires-Dist: twine>=4.0.0; extra == 'dev'
